[
  {
    "title": "The Quantum Paradox",
    "author": "Liam Vance",
    "isbn": "978-0-12-345678-9",
    "publisher": "Nova Books",
    "publication_year": 2023,
    "category": "Science Fiction",
    "rating": 4.7,
    "synopsis": "A physicist discovers a flaw in the fabric of reality that threatens to unravel the universe."
  },
  {
    "title": "Whispers in the Mist",
    "author": "Evelyn Reed",
    "isbn": "978-1-23-456789-0",
    "publisher": "Shadow Press",
    "publication_year": 2021,
    "category": "Mystery",
    "rating": 4.2,
    "synopsis": "A detective investigates a series of unexplained disappearances in a foggy, isolated coastal town."
  },
  {
    "title": "The Last Emperor",
    "author": "Julian Thorne",
    "isbn": "978-2-34-567890-1",
    "publisher": "History House",
    "publication_year": 2019,
    "category": "Fantasy",
    "rating": 4.5,
    "synopsis": "An epic tale of the final days of a magical empire, seen through the eyes of a young centurion."
  },
  {
    "title": "Algorithmic Dreams",
    "author": "Sarah Chen",
    "isbn": "978-3-45-678901-2",
    "publisher": "TechPrint",
    "publication_year": 2024,
    "category": "Technology",
    "rating": 4.8,
    "synopsis": "A deep dive into the future of artificial intelligence and its impact on human consciousness."
  },
  {
    "title": "Gardens of the Moon",
    "author": "Aria Solis",
    "isbn": "978-4-56-789012-3",
    "publisher": "Celestial Publishing",
    "publication_year": 2020,
    "category": "Fantasy",
    "rating": 4.6,
    "synopsis": "A young mage must learn to harness the power of lunar magic to save her kingdom from an ancient evil."
  },
  {
    "title": "The Art of Simplicity",
    "author": "Marcus Aurelius Jr.",
    "isbn": "978-5-67-890123-4",
    "publisher": "Zenith Books",
    "publication_year": 2022,
    "category": "Technology",
    "rating": 4.3,
    "synopsis": "A modern guide to minimalist living in a hyper-connected, technology-driven world."
  },
  {
    "title": "Culinary Journeys",
    "author": "Chef Isabella",
    "isbn": "978-6-78-901234-5",
    "publisher": "Gourmet Press",
    "publication_year": 2021,
    "category": "Mystery",
    "rating": 4.9,
    "synopsis": "A collection of exotic recipes intertwined with a gripping culinary murder mystery."
  },
  {
    "title": "Shadows of the Past",
    "author": "David Blackwood",
    "isbn": "978-7-89-012345-6",
    "publisher": "Mystery House",
    "publication_year": 2018,
    "category": "Mystery",
    "rating": 4.1,
    "synopsis": "An ex-spy is pulled back into the shadowy world of international espionage when an old friend is murdered."
  },
  {
    "title": "The Starry Expanse",
    "author": "Nova Stellaris",
    "isbn": "978-8-90-123456-7",
    "publisher": "Cosmos Books",
    "publication_year": 2025,
    "category": "Science Fiction",
    "rating": 4.4,
    "synopsis": "Humanity's first mission to another star system encounters something entirely unexpected."
  },
  {
    "title": "Financial Freedom",
    "author": "John Doe",
    "isbn": "978-9-01-234567-8",
    "publisher": "Wealth Builders",
    "publication_year": 2020,
    "category": "Technology",
    "rating": 4.0,
    "synopsis": "A step-by-step guide to taking control of your personal finances using modern fintech tools."
  },
  {
    "title": "The Forgotten Kingdom",
    "author": "Elena Rostova",
    "isbn": "978-0-11-223344-5",
    "publisher": "Mythos Publishing",
    "publication_year": 2017,
    "category": "Fantasy",
    "rating": 4.7,
    "synopsis": "An archeologist uncovers a lost magical civilization that challenges everything we know about history."
  },
  {
    "title": "Code Red",
    "author": "Alex Mercer",
    "isbn": "978-1-22-334455-6",
    "publisher": "CyberPress",
    "publication_year": 2023,
    "category": "Technology",
    "rating": 4.5,
    "synopsis": "A gripping account of the biggest cybersecurity breach of the 21st century and how it was stopped."
  },
  {
    "title": "Songs of the Sea",
    "author": "Captain Marina",
    "isbn": "978-2-33-445566-7",
    "publisher": "Oceanic Books",
    "publication_year": 2019,
    "category": "Fantasy",
    "rating": 4.2,
    "synopsis": "A collection of lyrical poems and tales of mythical sea creatures and forgotten ocean deities."
  },
  {
    "title": "Mindful Leadership",
    "author": "Robert Green",
    "isbn": "978-3-44-556677-8",
    "publisher": "Business Elite",
    "publication_year": 2021,
    "category": "Technology",
    "rating": 4.6,
    "synopsis": "How to lead tech companies with empathy, purpose, and clarity in today's fast-paced environment."
  },
  {
    "title": "The Crimson Blade",
    "author": "Kira Night",
    "isbn": "978-4-55-667788-9",
    "publisher": "Adventure Press",
    "publication_year": 2022,
    "category": "Mystery",
    "rating": 4.3,
    "synopsis": "A skilled assassin seeks revenge against the corrupt syndicate that betrayed her."
  },
  {
    "title": "Beyond the Horizon",
    "author": "Dr. Alan Grant",
    "isbn": "978-5-66-778899-0",
    "publisher": "Science Today",
    "publication_year": 2024,
    "category": "Science Fiction",
    "rating": 4.8,
    "synopsis": "Exploring the latest breakthroughs in space exploration and what lies beyond our solar system."
  },
  {
    "title": "The Healing Heart",
    "author": "Dr. Sarah Jenkins",
    "isbn": "978-6-77-889900-1",
    "publisher": "Wellness Books",
    "publication_year": 2020,
    "category": "Science Fiction",
    "rating": 4.4,
    "synopsis": "A tale of advanced futuristic medicine capable of healing emotional trauma through neuro-syncing."
  },
  {
    "title": "City of Brass",
    "author": "Omar Al-Fayed",
    "isbn": "978-7-88-990011-2",
    "publisher": "Desert Winds",
    "publication_year": 2018,
    "category": "Fantasy",
    "rating": 4.9,
    "synopsis": "A street thief is swept into a world of djinns and magic when he steals a mysterious artifact."
  },
  {
    "title": "The Silent Echo",
    "author": "M. L. Vance",
    "isbn": "978-8-99-001122-3",
    "publisher": "Suspense Reads",
    "publication_year": 2015,
    "category": "Mystery",
    "rating": 4.1,
    "synopsis": "A psychological thriller about a woman's act of violence against her husband—and of the therapist obsessed with uncovering her motive."
  },
  {
    "title": "Digital Nomads",
    "author": "Alex Rivera",
    "isbn": "978-9-00-112233-4",
    "publisher": "Lifestyle Publishing",
    "publication_year": 2023,
    "category": "Technology",
    "rating": 4.5,
    "synopsis": "A guide to traveling the world while building a successful remote career in the digital age."
  }
]
